pygetsource/__init__.py
pygetsource/ast_utils.py
pygetsource/decompiler.py
pygetsource/factory.py
pygetsource/utils.py
pygetsource-0.4.0.dist-info/licenses/LICENSE
pygetsource-0.4.0.dist-info/METADATA
pygetsource-0.4.0.dist-info/WHEEL
pygetsource-0.4.0.dist-info/top_level.txt
pygetsource-0.4.0.dist-info/RECORD
