Metadata-Version: 2.4
Name: pygetsource
Version: 0.4.0
Summary: A Python 3 decompiler
Author-email: Perceval Wajsbürt <perceval.wajsburt@gmail.com>
License: MIT License
Project-URL: homepage, https://github.com/percevalw/pygetsource/
Project-URL: repository, https://github.com/percevalw/pygetsource/
Classifier: Development Status :: 3 - Alpha
Classifier: Intended Audience :: Developers
Classifier: License :: OSI Approved :: MIT License
Classifier: Operating System :: OS Independent
Classifier: Programming Language :: Python :: 3
Classifier: Programming Language :: Python :: 3.7
Classifier: Programming Language :: Python :: 3.8
Classifier: Programming Language :: Python :: 3.9
Classifier: Programming Language :: Python :: 3.10
Classifier: Programming Language :: Python :: 3.11
Classifier: Topic :: Software Development :: Libraries :: Python Modules
Classifier: Topic :: Software Development :: Code Generators
Classifier: Topic :: Software Development :: Disassemblers
Classifier: Topic :: Software Development :: Pre-processors
Classifier: Topic :: Utilities
Requires-Python: <4.0,>=3.7
License-File: LICENSE
Requires-Dist: astunparse
Requires-Dist: typing_extensions
Provides-Extra: dev
Requires-Dist: pytest; extra == "dev"
Requires-Dist: pytest-cov; extra == "dev"
Requires-Dist: coverage[toml]>=7.2.0; extra == "dev"
Requires-Dist: networkx<4.0,>=2.0.0; extra == "dev"
Requires-Dist: pygraphviz<2.0,>=1.7; extra == "dev"
Requires-Dist: ipython<8.0.0,>=6.0.0; extra == "dev"
Dynamic: license-file
